openvector/__init__.py
openvector/client.py
openvector/collection.py
openvector/openvector.py
openvector/query_result.py
openvector-0.0.3.dist-info/LICENSE
openvector-0.0.3.dist-info/METADATA
openvector-0.0.3.dist-info/WHEEL
openvector-0.0.3.dist-info/top_level.txt
openvector-0.0.3.dist-info/RECORD
