Metadata-Version: 2.1
Name: openvector
Version: 0.0.3
Summary: An open source vector embeddings database.
Home-page: https://github.com/eddyjin1/openvector
Author: Eddy Jin
Classifier: Programming Language :: Python :: 3
Classifier: License :: OSI Approved :: MIT License
Classifier: Operating System :: OS Independent
Requires-Python: >=3.6
License-File: LICENSE
